[
  {
    "Production/Technology": "Total",
    "Cement Capacity": 745.8,
    "Country": "India"
  },
  {
    "Production/Technology": "CCS/CCUS",
    "Cement Capacity": 0,
    "Country": "India"
  },
  {
    "Production/Technology": "Alternative Fuel",
    "Cement Capacity": 91.9,
    "Country": "India"
  },
  {
    "Production/Technology": "Clay Calcination",
    "Cement Capacity": 4.75,
    "Country": "India"
  },
  {
    "Production/Technology": "Total",
    "Cement Capacity": 110.7,
    "Country": "Brazil"
  },
  {
    "Production/Technology": "CCS/CCUS",
    "Cement Capacity": 0,
    "Country": "Brazil"
  },
  {
    "Production/Technology": "Alternative Fuel",
    "Cement Capacity": 34.7,
    "Country": "Brazil"
  },
  {
    "Production/Technology": "Clay Calcination",
    "Cement Capacity": 5,
    "Country": "Brazil"
  },
  {
    "Production/Technology": "Total",
    "Cement Capacity": 102,
    "Country": "United States of America"
  },
  {
    "Production/Technology": "CCS/CCUS",
    "Cement Capacity": 7.9,
    "Country": "United States of America"
  },
  {
    "Production/Technology": "Alternative Fuel",
    "Cement Capacity": 66.9,
    "Country": "United States of America"
  },
  {
    "Production/Technology": "Clay Calcination",
    "Cement Capacity": 0,
    "Country": "United States of America"
  }
 ]
